{"metadata":{"en":"Feb/Mar 2015","np":"फाल्गुन २०७१"},"days":[{"n":"","e":"","t":"","f":"","h":false,"d":1},{"n":"","e":"","t":"","f":"","h":false,"d":2},{"n":"","e":"","t":"","f":"","h":false,"d":3},{"n":"","e":"","t":"","f":"","h":false,"d":4},{"n":"","e":"","t":"","f":"","h":false,"d":5},{"n":"१","e":"13","t":"नवमी","f":"","h":false,"d":6},{"n":"२","e":"14","t":"दशमी","f":"","h":true,"d":7},{"n":"३","e":"15","t":"एकादशी","f":"विजया एकादशी व्रत","h":false,"d":1},{"n":"४","e":"16","t":"द्वादशी","f":"","h":false,"d":2},{"n":"५","e":"17","t":"त्रयोदशी","f":"महाशिवरात्रि","h":true,"d":3},{"n":"६","e":"18","t":"चतुर्दशी","f":"","h":false,"d":4},{"n":"७","e":"19","t":"प्रतिपदा","f":"प्रजातन्त्र दिवस,घ्याल्पो ल्होसार","h":true,"d":5},{"n":"८","e":"20","t":"द्दितीया","f":"","h":false,"d":6},{"n":"९","e":"21","t":"तृतीया","f":"","h":true,"d":7},{"n":"१०","e":"22","t":"चतुर्थी","f":"","h":false,"d":1},{"n":"११","e":"23","t":"पञ्चमी","f":"","h":false,"d":2},{"n":"१२","e":"24","t":"षष्ठी","f":"","h":false,"d":3},{"n":"१३","e":"25","t":"सप्तमी","f":"","h":false,"d":4},{"n":"१४","e":"26","t":"अष्टमी","f":"चिरोत्यान, होलि आरम्भ","h":false,"d":5},{"n":"१५","e":"27","t":"नवमी","f":"","h":false,"d":6},{"n":"१६","e":"28","t":"दशमी","f":"","h":true,"d":7},{"n":"१७","e":"01","t":"एकादशी","f":"आमलकि एकादशी व्रत","h":false,"d":1},{"n":"१८","e":"02","t":"द्वादशी","f":"","h":false,"d":2},{"n":"१९","e":"03","t":"त्रयोदशी","f":"","h":false,"d":3},{"n":"२०","e":"04","t":"चतुर्दशी","f":"","h":false,"d":4},{"n":"२१","e":"05","t":"पुर्णिमा","f":"फागु पुर्णिमा  (पहाडी ५५ जिल्लामा विदा)","h":false,"d":5},{"n":"२२","e":"06","t":"प्रतिपदा","f":"फागु पुर्णिमा(तराइ विदा)","h":false,"d":6},{"n":"२३","e":"07","t":"द्दितीया","f":"","h":true,"d":7},{"n":"२४","e":"08","t":"तृतीया","f":"अन्तराष्ट्रिय नारी दिवस","h":true,"d":1},{"n":"२५","e":"09","t":"चतुर्थी","f":"","h":false,"d":2},{"n":"२६","e":"10","t":"पञ्चमी","f":"","h":false,"d":3},{"n":"२७","e":"11","t":"पञ्चमी","f":"","h":false,"d":4},{"n":"२८","e":"12","t":"षष्ठी","f":"","h":false,"d":5},{"n":"२९","e":"13","t":"सप्तमी","f":"","h":false,"d":6},{"n":"३०","e":"14","t":"अष्टमी","f":"","h":true,"d":7}],"holiFest":["३ गते विजया एकादशी व्रत","५ गते महाशिवरात्रि","७ गते राष्ट्रिय प्रजातन्त्र दिवस, घ्याल्पो ल्होसार ","१४ गते चिरोत्यान, होलि आरम्भ ","१७ गते आमलकि एकादशी व्रत","२१ गते फागु पुर्णिमा (पहाडी ५५ जिल्लामा विदा)","२२ गते  प्रतिपदा (तराइ तथा भित्री मधेशका २० जिल्लामा फागु पुर्णिमा विदा)","२४ गते अन्तराष्ट्रिय नारी दिवस"],"marriage":["२ ,१३ ,१४ ,१५ ,२० ,२५ ,२६ ,२९ र ३०  गते"],"bratabandha":["८ र ११  गते"]}